Mopidy_Lagukan-0.2.4.dist-info/DESCRIPTION.rst
Mopidy_Lagukan-0.2.4.dist-info/METADATA
Mopidy_Lagukan-0.2.4.dist-info/RECORD
Mopidy_Lagukan-0.2.4.dist-info/WHEEL
Mopidy_Lagukan-0.2.4.dist-info/entry_points.txt
Mopidy_Lagukan-0.2.4.dist-info/metadata.json
Mopidy_Lagukan-0.2.4.dist-info/top_level.txt
mopidy_lagukan/__init__.py
mopidy_lagukan/commands.py
mopidy_lagukan/ext.conf
mopidy_lagukan/frontend.py
mopidy_lagukan/static/index.html
