Metadata-Version: 2.0
Name: Mopidy-Lagukan
Version: 0.2.4
Summary: Mopidy extension for Lagukan
Home-page: https://github.com/jacobobryant/mopidy-lagukan
Author: Jacob O'Bryant
Author-email: foo@jacobobryant.com
License: Apache License, Version 2.0
Platform: UNKNOWN
Classifier: Environment :: No Input/Output (Daemon)
Classifier: Intended Audience :: End Users/Desktop
Classifier: License :: OSI Approved :: Apache Software License
Classifier: Operating System :: OS Independent
Classifier: Programming Language :: Python :: 2
Classifier: Topic :: Multimedia :: Sound/Audio :: Players
Requires-Dist: Mopidy (>=1.0)
Requires-Dist: Pykka (>=1.1)
Requires-Dist: setuptools
